git_feature_notion/__init__.py
git_feature_notion/cli.py
git_feature_notion/git_feature_notion.py
git_notion/__init__.py
git_notion/cli.py
git_notion/git_notion.py
git_feature_notion-1.0.2.dist-info/LICENSE
git_feature_notion-1.0.2.dist-info/METADATA
git_feature_notion-1.0.2.dist-info/WHEEL
git_feature_notion-1.0.2.dist-info/entry_points.txt
git_feature_notion-1.0.2.dist-info/top_level.txt
git_feature_notion-1.0.2.dist-info/RECORD
