Metadata-Version: 2.1
Name: git-feature-notion
Version: 1.0.2
Summary: Syncs Github Markdown or any files to Notion
Home-page: https://github.com/radical-app/git-feature-notion
Author: NarekA
License: MIT license
Keywords: git_feature_notion
Classifier: Development Status :: 2 - Pre-Alpha
Classifier: Intended Audience :: Developers
Classifier: License :: OSI Approved :: MIT License
Classifier: Natural Language :: English
Classifier: Programming Language :: Python :: 3
Classifier: Programming Language :: Python :: 3.5
Classifier: Programming Language :: Python :: 3.6
Classifier: Programming Language :: Python :: 3.7
Classifier: Programming Language :: Python :: 3.8
Requires-Python: >=3.5
License-File: LICENSE
Requires-Dist: click
Requires-Dist: md2notion
Requires-Dist: notion
